jeanny3/__init__.py
jeanny3/jeanny3.py
jeanny3-0.2.dist-info/LICENSE.md
jeanny3-0.2.dist-info/METADATA
jeanny3-0.2.dist-info/WHEEL
jeanny3-0.2.dist-info/top_level.txt
jeanny3-0.2.dist-info/RECORD
