Metadata-Version: 2.1
Name: jeanny3
Version: 0.2
Summary: Simple and efficient document-oriented in-memory storage
Home-page: UNKNOWN
Author: Roman Kochanov
Author-email: 
License: UNKNOWN
Platform: UNKNOWN
Classifier: Programming Language :: Python :: 3
Classifier: License :: OSI Approved :: MIT License
Classifier: Operating System :: OS Independent
Requires-Python: >=3.5
